cycletls/__init__.py
cycletls/__version__.py
cycletls/_config.py
cycletls/_ffi.py
cycletls/_global.py
cycletls/api.py
cycletls/async_api.py
cycletls/exceptions.py
cycletls/fingerprints.py
cycletls/plugins.py
cycletls/schema.py
cycletls/sessions.py
cycletls/sse.py
cycletls/structures.py
cycletls/websocket.py
cycletls/dist/libcycletls.h
cycletls/dist/libcycletls.so
cycletls-0.0.3.dist-info/METADATA
cycletls-0.0.3.dist-info/WHEEL
cycletls-0.0.3.dist-info/RECORD
