Metadata-Version: 2.4
Name: cycletls
Version: 0.0.3
Summary: Advanced TLS fingerprinting library with JA3, JA4, HTTP/2, HTTP/3, WebSocket, and SSE support - bypass anti-bot detection by impersonating real browsers
Project-URL: Homepage, https://github.com/Danny-Dasilva/cycletls_python
Project-URL: Documentation, https://github.com/Danny-Dasilva/cycletls_python#readme
Project-URL: Repository, https://github.com/Danny-Dasilva/cycletls_python
Project-URL: Bug Tracker, https://github.com/Danny-Dasilva/cycletls_python/issues
Author-email: Danny-Dasilva <dannydasilva.solutions@gmail.com>
License: MIT
Keywords: akamai-fingerprint,anti-bot,bot-detection-bypass,browser-impersonation,cloudflare-bypass,curl-impersonate,fingerprinting,http-client,http2,http2-fingerprint,http3,ja3,ja3-fingerprint,ja4,quic,requests,sse,tls,tls-fingerprint,web-scraping,websocket
Classifier: Development Status :: 4 - Beta
Classifier: Intended Audience :: Developers
Classifier: License :: OSI Approved :: MIT License
Classifier: Programming Language :: Python :: 3
Classifier: Programming Language :: Python :: 3.10
Classifier: Programming Language :: Python :: 3.11
Classifier: Programming Language :: Python :: 3.12
Classifier: Programming Language :: Python :: 3.13
Classifier: Programming Language :: Python :: 3.14
Classifier: Topic :: Internet :: WWW/HTTP
Classifier: Topic :: Security
Classifier: Topic :: Software Development :: Libraries :: Python Modules
Requires-Python: >=3.10
Requires-Dist: cffi>=1.15.0
Requires-Dist: orjson>=3.9.0
Requires-Dist: ormsgpack>=1.5.0
Requires-Dist: pydantic>=2.0.0
Requires-Dist: websocket-client>=1.0.0
Requires-Dist: websockets>=10.0
Provides-Extra: benchmark
Requires-Dist: aiohttp>=3.8.0; extra == 'benchmark'
Requires-Dist: curl-cffi>=0.5.0; extra == 'benchmark'
Requires-Dist: hrequests>=0.7.0; extra == 'benchmark'
Requires-Dist: httpx>=0.24.0; extra == 'benchmark'
Requires-Dist: matplotlib>=3.7.0; extra == 'benchmark'
Requires-Dist: niquests>=3.0.0; extra == 'benchmark'
Requires-Dist: pandas>=2.0.0; extra == 'benchmark'
Requires-Dist: primp>=0.6.0; extra == 'benchmark'
Requires-Dist: pycurl>=7.45.0; extra == 'benchmark'
Requires-Dist: requests>=2.31.0; extra == 'benchmark'
Requires-Dist: rnet>=0.0.1; extra == 'benchmark'
Requires-Dist: tls-client>=0.2.0; extra == 'benchmark'
Requires-Dist: uvloop>=0.17.0; (sys_platform != 'win32') and extra == 'benchmark'
Provides-Extra: dev
Requires-Dist: build>=1.0.0; extra == 'dev'
Requires-Dist: pyright>=1.1.390; extra == 'dev'
Requires-Dist: pytest-asyncio>=0.18.0; extra == 'dev'
Requires-Dist: pytest-rerunfailures>=14.0; extra == 'dev'
Requires-Dist: pytest-xdist>=3.0.0; extra == 'dev'
Requires-Dist: pytest>=7.0.0; extra == 'dev'
Requires-Dist: ruff>=0.8.0; extra == 'dev'
Provides-Extra: docs
Requires-Dist: furo>=2023.0.0; extra == 'docs'
Requires-Dist: myst-parser>=2.0.0; extra == 'docs'
Requires-Dist: requests>=2.31.0; extra == 'docs'
Requires-Dist: sphinx-autodoc-typehints>=1.23.0; extra == 'docs'
Requires-Dist: sphinx-copybutton>=0.5.0; extra == 'docs'
Requires-Dist: sphinx<9.0.0,>=7.0.0; extra == 'docs'
